akshare_one_mcp/__init__.py
akshare_one_mcp/__main__.py
akshare_one_mcp/server.py
akshare_one_mcp-0.3.8.dist-info/WHEEL
akshare_one_mcp-0.3.8.dist-info/entry_points.txt
akshare_one_mcp-0.3.8.dist-info/METADATA
akshare_one_mcp-0.3.8.dist-info/RECORD
