Metadata-Version: 2.3
Name: akshare-one-mcp
Version: 0.3.8
Summary: MCP server that provides access to Chinese stock market data using akshare-one
Keywords: akshare,stock,mcp,mcp-server
Author: zwldarren
Author-email: zwldarren <zwldarren@gmail.com>
License: MIT
Requires-Dist: akshare-one>=0.3.14
Requires-Dist: fastmcp>=2.11.3
Requires-Dist: uvicorn>=0.35.0
Requires-Python: >=3.12
Project-URL: Homepage, https://github.com/zwldarren/akshare-one-mcp
Project-URL: Repository, https://github.com/zwldarren/akshare-one-mcp.git
